mrilabs/__init__.py
mrilabs/__main__.py
mrilabs/api/__init__.py
mrilabs/api/dg4202_api.py
mrilabs/app.py
mrilabs/assets/favicon.ico
mrilabs/device/__init__.py
mrilabs/device/data.py
mrilabs/device/device.py
mrilabs/device/dg4202.py
mrilabs/device/edux1002a.py
mrilabs/device/interface.py
mrilabs/frontend/__init__.py
mrilabs/frontend/header.py
mrilabs/frontend/managers/__init__.py
mrilabs/frontend/managers/device.py
mrilabs/frontend/managers/dg4202.py
mrilabs/frontend/managers/edux1002a.py
mrilabs/frontend/managers/state_manager.py
mrilabs/frontend/pages/__init__.py
mrilabs/frontend/pages/factory.py
mrilabs/frontend/pages/general.py
mrilabs/frontend/pages/monitor.py
mrilabs/frontend/pages/plotter.py
mrilabs/frontend/pages/scheduler.py
mrilabs/frontend/pages/settings.py
mrilabs/frontend/tasks/__init__.py
mrilabs/frontend/tasks/config_loader.py
mrilabs/frontend/tasks/model.py
mrilabs/frontend/tasks/task_decorator.py
mrilabs/frontend/tasks/task_validator.py
mrilabs/frontend/tasks/tasks.py
mrilabs/frontend/widgets/__init__.py
mrilabs/frontend/widgets/gen_oscilloscope.py
mrilabs/frontend/widgets/gen_signal.py
mrilabs/frontend/widgets/menu.py
mrilabs/frontend/widgets/mon_device.py
mrilabs/frontend/widgets/sch_exp_popup.py
mrilabs/frontend/widgets/sch_experiments.py
mrilabs/frontend/widgets/sch_scheduler.py
mrilabs/frontend/widgets/sch_task_parameters.py
mrilabs/frontend/widgets/sch_task_popup.py
mrilabs/frontend/widgets/set_mock.py
mrilabs/frontend/widgets/set_state.py
mrilabs/frontend/widgets/sidebar.py
mrilabs/frontend/widgets/templates.py
mrilabs/frontend/widgets/ui_factory.py
mrilabs/frontend/widgets/windows.py
mrilabs/scheduler/functionmap.py
mrilabs/scheduler/models.py
mrilabs/scheduler/registry.py
mrilabs/scheduler/timekeeper.py
mrilabs/scheduler/worker.py
mrilabs/utils/__init__.py
mrilabs/utils/logging.py
mrilabs-0.1.2.dist-info/LICENSE
mrilabs-0.1.2.dist-info/METADATA
mrilabs-0.1.2.dist-info/WHEEL
mrilabs-0.1.2.dist-info/RECORD
